pytest_uncollect_if/__init__.py
pytest_uncollect_if/plugin.py
pytest_uncollect_if/py.typed
pytest_uncollect_if-0.1.3.dist-info/LICENSE
pytest_uncollect_if-0.1.3.dist-info/METADATA
pytest_uncollect_if-0.1.3.dist-info/WHEEL
pytest_uncollect_if-0.1.3.dist-info/entry_points.txt
pytest_uncollect_if-0.1.3.dist-info/top_level.txt
pytest_uncollect_if-0.1.3.dist-info/RECORD
