Metadata-Version: 2.1
Name: pytest-uncollect-if
Version: 0.1.3
Summary: A plugin to uncollect pytests tests rather than using skipif
Author-email: Jason Giancono <jasongiancono@gmail.com>
Maintainer-email: Jason Giancono <jasongiancono@gmail.com>
License: 
Project-URL: Repository, https://github.com/jasongi/pytest-uncollect-if
Classifier: Framework :: Pytest
Classifier: Development Status :: 4 - Beta
Classifier: Intended Audience :: Developers
Classifier: Topic :: Software Development :: Testing
Classifier: Operating System :: OS Independent
Classifier: Programming Language :: Python
Classifier: Programming Language :: Python :: 3.9
Classifier: Programming Language :: Python :: 3.10
Classifier: Programming Language :: Python :: 3.11
Classifier: Programming Language :: Python :: 3.12
Classifier: Programming Language :: Python :: 3.13
Classifier: Programming Language :: Python :: 3 :: Only
Classifier: Programming Language :: Python :: Implementation :: CPython
Classifier: Programming Language :: Python :: Implementation :: PyPy
Classifier: License :: OSI Approved :: MIT License
Requires-Python: >=3.9
License-File: LICENSE
Requires-Dist: pytest>=6.2.0
